LICENSE
README.md
setup.py
NER/__init__.py
NER/AutoProcessor/__init__.py
NER/AutoProcessor/ParseTree/TreeAutoNER.py
NER/AutoProcessor/ParseTree/__init__.py
NER/AutoProcessor/Sentence/SentenceAutoNER.py
NER/AutoProcessor/Sentence/TurkishSentenceAutoNER.py
NER/AutoProcessor/Sentence/__init__.py
NlpToolkit_NER.egg-info/PKG-INFO
NlpToolkit_NER.egg-info/SOURCES.txt
NlpToolkit_NER.egg-info/dependency_links.txt
NlpToolkit_NER.egg-info/requires.txt
NlpToolkit_NER.egg-info/top_level.txt