Metadata-Version: 2.1
Name: NlpToolkit-NER
Version: 1.0.3
Summary: NER library
Home-page: https://github.com/StarlangSoftware/NER-Py
Author: olcaytaner
Author-email: olcay.yildiz@ozyegin.edu.tr
License: UNKNOWN
Platform: UNKNOWN
License-File: LICENSE
